morelists/__init__.py
morelists-0.1.8.dist-info/licenses/LICENSE
morelists-0.1.8.dist-info/METADATA
morelists-0.1.8.dist-info/WHEEL
morelists-0.1.8.dist-info/top_level.txt
morelists-0.1.8.dist-info/RECORD
