Metadata-Version: 2.4
Name: morelists
Version: 0.1.8
Summary: A small and easy list you can add together like a math equation and has a expiration date for items. Mostly useful for games with stats from multiple sources. More lists will come soon.
Home-page: https://github.com/EmanuelNorsk/enlist
Author: Emanuel Odén Hesselroth
Author-email: Emanuel Odén Hesselroth <emanuelodenhesselroth@gmail.com>
License: MIT
Classifier: Programming Language :: Python :: 3
Classifier: License :: OSI Approved :: MIT License
Classifier: Operating System :: OS Independent
Requires-Python: >=3.6
License-File: LICENSE
Dynamic: author
Dynamic: home-page
Dynamic: license-file
